hfmirror/__init__.py
hfmirror/config/__init__.py
hfmirror/config/meta.py
hfmirror/resource/__init__.py
hfmirror/resource/github.py
hfmirror/resource/item.py
hfmirror/resource/local.py
hfmirror/resource/resource.py
hfmirror/resource/sourceforge.py
hfmirror/resource/version.py
hfmirror/storage/__init__.py
hfmirror/storage/base.py
hfmirror/storage/huggingface.py
hfmirror/storage/local.py
hfmirror/sync/__init__.py
hfmirror/sync/sync.py
hfmirror/utils/__init__.py
hfmirror/utils/download.py
hfmirror/utils/filepool.py
hfmirror/utils/hash.py
hfmirror/utils/segments.py
hfmirror/utils/session.py
hfmirror/utils/text.py
hfmirror-0.0.7.dist-info/LICENSE
hfmirror-0.0.7.dist-info/METADATA
hfmirror-0.0.7.dist-info/WHEEL
hfmirror-0.0.7.dist-info/top_level.txt
hfmirror-0.0.7.dist-info/RECORD
